poetry_aliases/__init__.py
poetry_aliases/commands.py
poetry_aliases/plugin.py
poetry_aliases-1.0.1.dist-info/METADATA
poetry_aliases-1.0.1.dist-info/entry_points.txt
poetry_aliases-1.0.1.dist-info/WHEEL
poetry_aliases-1.0.1.dist-info/LICENSE.md
poetry_aliases-1.0.1.dist-info/RECORD
