Metadata-Version: 2.1
Name: poetry-aliases
Version: 1.0.1
Summary: Create aliases for Poetry commands
Home-page: https://github.com/celsiusnarhwal/poetry-aliases
Author: celsius narhwal
Author-email: hello@celsiusnarhwal.dev
Requires-Python: >=3.7,<4.0
Classifier: Programming Language :: Python :: 3
Classifier: Programming Language :: Python :: 3.7
Classifier: Programming Language :: Python :: 3.8
Classifier: Programming Language :: Python :: 3.9
Classifier: Programming Language :: Python :: 3.10
Classifier: Programming Language :: Python :: 3.11
Requires-Dist: click (>=8.1.3,<9.0.0)
Requires-Dist: poetry (>=1.3.2,<2.0.0)
